<?xml version = '1.0' encoding = 'UTF-8'?>
<TableProxyOraclev11g class="oracle.dbtools.crest.model.design.storage.oracle.v11g.TableProxyOraclev11g" name="TBL_MARCAS" directorySegmentName="seg_0" id="DEEF94DC-1633-431F-AE2C-86D87367BF5E">
<createdBy>Konqueror</createdBy>
<createdTime>2015-06-11 15:06:12 UTC</createdTime>
<ownerDesignName>modelo_relacional_aerolinea</ownerDesignName>
<schemaObject>736E312B-6B9F-9999-CD1F-691C10BD74F0</schemaObject>
<logging>YES</logging>
<partitionedRowMovement>DISABLE</partitionedRowMovement>
<temporaryChanged>false</temporaryChanged>
<accessDriverType>oracle_loader</accessDriverType>
<rejectLimit></rejectLimit>
<columnProxies itemClass="oracle.dbtools.crest.model.design.storage.oracle.v12c.ColumnProxyOraclev12c">
<ColumnProxy name="NOMBRE_MARCA" id="22C6626A-BC37-F824-BCD8-744381287B0B">
<createdBy>Konqueror</createdBy>
<createdTime>2015-06-11 15:06:12 UTC</createdTime>
<ownerDesignName>modelo_relacional_aerolinea</ownerDesignName>
</ColumnProxy>
<ColumnProxy name="CODIGO_MARCA" id="E803B95A-781F-3E99-DE7A-BC6973D94528">
<createdBy>Konqueror</createdBy>
<createdTime>2015-06-11 15:06:12 UTC</createdTime>
<ownerDesignName>modelo_relacional_aerolinea</ownerDesignName>
</ColumnProxy>
</columnProxies>
<primaryKeys>
<PrimaryKey class="oracle.dbtools.crest.model.design.storage.oracle.v10g.PKProxyOraclev10g" name="TBL_MARCAS_PK" id="52C46817-132E-1C99-F97B-4C66054A83B4">
<createdBy>Konqueror</createdBy>
<createdTime>2015-06-11 15:06:12 UTC</createdTime>
<ownerDesignName>modelo_relacional_aerolinea</ownerDesignName>
<indexSort>SORTED</indexSort>
</PrimaryKey>
</primaryKeys>
</TableProxyOraclev11g>